pip_importer/__init__.py
pip_importer/py.typed
pip_importer-0.2.0.dist-info/METADATA
pip_importer-0.2.0.dist-info/WHEEL
pip_importer-0.2.0.dist-info/entry_points.txt
pip_importer-0.2.0.dist-info/top_level.txt
pip_importer-0.2.0.dist-info/RECORD
